jsonr/__init__.py
jsonr/__main__.py
jsonr/help.py
jsonr/_core/__init__.py
jsonr/_core/_binary.py
jsonr/_core/_code.py
jsonr/_core/_concurrent.py
jsonr/_core/_crypto.py
jsonr/_core/_data.py
jsonr/_core/_dcompress.py
jsonr/_core/_debug.py
jsonr/_core/_devtools.py
jsonr/_core/_dtypes.py
jsonr/_core/_file.py
jsonr/_core/_formats.py
jsonr/_core/_functional.py
jsonr/_core/_guitk.py
jsonr/_core/_idata.py
jsonr/_core/_import.py
jsonr/_core/_international.py
jsonr/_core/_iprotocols.py
jsonr/_core/_language.py
jsonr/_core/_markup.py
jsonr/_core/_math.py
jsonr/_core/_mswindows.py
jsonr/_core/_multimedia.py
jsonr/_core/_networking.py
jsonr/_core/_os.py
jsonr/_core/_packaging.py
jsonr/_core/_program.py
jsonr/_core/_runtime.py
jsonr/_core/_superseded.py
jsonr/_core/_text.py
jsonr/_core/_unix.py
jsonr/_typing/__init__.py
jsonr/_typing/jsonr_typing_flowa.py
jsonr/_typing/jsonr_typing_json.py
jsonr/_typing/jsonr_typing_pollinations.py
jsonr/_typing/jsonr_typing_string.py
jsonr/_utils/__init__.py
jsonr/_utils/_bond.py
jsonr/_utils/_convertions.py
jsonr/_utils/_infinity.py
jsonr/_utils/_inspect.py
jsonr/bases/__init__.py
jsonr/bases/new_base.py
jsonr/core/__init__.py
jsonr/core/dataframe.py
jsonr/core/new.py
jsonr/libs/__init__.py
jsonr/libs/flowa/__init__.py
jsonr/libs/flowa/_version.py
jsonr/libs/flowa/main/__init__.py
jsonr/libs/flowa/main/decisiontree.py
jsonr/libs/flowa/main/imagemodel.py
jsonr/libs/flowa/main/labelencoder.py
jsonr/libs/flowa/types/__init__.py
jsonr/libs/flowa/utils/__init__.py
jsonr/libs/pollinations/__init__.py
jsonr/libs/pollinations/abc/__init__.py
jsonr/libs/pollinations/abc/imageprotocol.py
jsonr/libs/pollinations/abc/textprotocol.py
jsonr/libs/pollinations/ai/__init__.py
jsonr/libs/pollinations/ext/__init__.py
jsonr/libs/pollinations/types/ImageModel.py
jsonr/libs/pollinations/types/ImageObject.py
jsonr/libs/pollinations/types/TextModel.py
jsonr/libs/pollinations/types/TextObject.py
jsonr/libs/pollinations/types/__init__.py
jsonr/typing/__init__.py
jsonr-8.6.6.dist-info/AUTHORS
jsonr-8.6.6.dist-info/LICENSE
jsonr-8.6.6.dist-info/METADATA
jsonr-8.6.6.dist-info/WHEEL
jsonr-8.6.6.dist-info/top_level.txt
jsonr-8.6.6.dist-info/RECORD
