Metadata-Version: 2.1
Name: jsonr
Version: 8.6.6
Summary: Highly customizable JSON objects and dataframes, and your python toolkit all in one.
Home-page: https://github.com/jsonr-py/jsonr
Author: jsonr
Author-email: jsonr <jsonr.py@gmail.com>
License: MIT License
Project-URL: GitHub, https://github.com/jsonr-py
Project-URL: Repository, https://github.com/jsonr-py/jsonr
Project-URL: PyPi, https://pypi.org/project/jsonr
Keywords: jsonr,json,jsonr-py,jsonr-python,python
Classifier: Development Status :: 5 - Production/Stable
Classifier: Intended Audience :: Developers
Classifier: Topic :: Software Development :: Build Tools
Classifier: License :: OSI Approved :: MIT License
Classifier: Programming Language :: Python :: 3
Classifier: Programming Language :: Python :: 3.7
Requires-Python: >=3.7
License-File: LICENSE
License-File: AUTHORS
Requires-Dist: numpy
Requires-Dist: requests
Requires-Dist: pathlib
Requires-Dist: pandas
Requires-Dist: google-generativeai
